llama_index/digitalocean/__init__.py
llama_index/digitalocean/embeddings/__init__.py
llama_index/digitalocean/embeddings/base.py
llama_index_digitalocean_embeddings-0.1.7.dist-info/licenses/LICENSE
llama_index_digitalocean_embeddings-0.1.7.dist-info/METADATA
llama_index_digitalocean_embeddings-0.1.7.dist-info/WHEEL
llama_index_digitalocean_embeddings-0.1.7.dist-info/top_level.txt
llama_index_digitalocean_embeddings-0.1.7.dist-info/RECORD
