Metadata-Version: 2.4
Name: llama-index-digitalocean-embeddings
Version: 0.1.7
Summary: DigitalOcean AI embeddings integration for LlamaIndex.
Author: LlamaIndex Contributors
License: Apache License
Project-URL: Homepage, https://github.com/llama-index-digitalocean-embeddings
Project-URL: Issues, https://github.com/llama-index-digitalocean-embeddings/issues
Keywords: llama-index,embeddings,digitalocean,ai
Requires-Python: >=3.9
License-File: LICENSE
Requires-Dist: llama-index-core>=0.10.0
Requires-Dist: requests>=2.31.0
Dynamic: license-file
